matheo/__init__.py
matheo/_version.py
matheo/band_integration/__init__.py
matheo/band_integration/band_integration.py
matheo/band_integration/srf_utils.py
matheo/band_integration/tests/__init__.py
matheo/band_integration/tests/test_band_integration.py
matheo/utils/__init__.py
matheo/utils/function_def.py
matheo/utils/punpy_util.py
matheo/utils/tests/__init__.py
matheo/utils/tests/test_function_def.py
matheo/utils/tests/test_punpy_util.py
matheo-0.1.6.dist-info/licenses/LICENSE
matheo-0.1.6.dist-info/METADATA
matheo-0.1.6.dist-info/WHEEL
matheo-0.1.6.dist-info/top_level.txt
matheo-0.1.6.dist-info/RECORD
