Metadata-Version: 2.4
Name: matheo
Version: 0.1.6
Summary: Matheo is a python package with mathematical algorithms for use in Earth observation data and tools
Home-page: https://github.com/meteor-toolkit/matheo
Author: Sam Hunt, Pieter De Vis
Author-email: sam.hunt@npl.co.uk
License: None
License-File: LICENSE
Requires-Dist: pyspectral
Requires-Dist: comet_maths>=1.0.5
Requires-Dist: punpy>=1.0.4
Provides-Extra: dev
Requires-Dist: pre-commit; extra == "dev"
Requires-Dist: tox; extra == "dev"
Requires-Dist: sphinx; extra == "dev"
Requires-Dist: sphinx_design; extra == "dev"
Requires-Dist: sphinx_book_theme; extra == "dev"
Requires-Dist: ipython; extra == "dev"
Requires-Dist: sphinx_autosummary_accessors; extra == "dev"
Dynamic: author
Dynamic: author-email
Dynamic: description
Dynamic: home-page
Dynamic: license
Dynamic: license-file
Dynamic: provides-extra
Dynamic: requires-dist
Dynamic: summary
